openvino_xai/__init__.py
openvino_xai/api/__init__.py
openvino_xai/api/api.py
openvino_xai/common/__init__.py
openvino_xai/common/parameters.py
openvino_xai/common/utils.py
openvino_xai/explainer/__init__.py
openvino_xai/explainer/explainer.py
openvino_xai/explainer/explanation.py
openvino_xai/explainer/utils.py
openvino_xai/explainer/visualizer.py
openvino_xai/inserter/__init__.py
openvino_xai/inserter/inserter.py
openvino_xai/inserter/model_parser.py
openvino_xai/methods/__init__.py
openvino_xai/methods/base.py
openvino_xai/methods/factory.py
openvino_xai/methods/black_box/__init__.py
openvino_xai/methods/black_box/base.py
openvino_xai/methods/black_box/rise.py
openvino_xai/methods/black_box/utils.py
openvino_xai/methods/black_box/aise/__init__.py
openvino_xai/methods/black_box/aise/base.py
openvino_xai/methods/black_box/aise/classification.py
openvino_xai/methods/black_box/aise/detection.py
openvino_xai/methods/white_box/__init__.py
openvino_xai/methods/white_box/activation_map.py
openvino_xai/methods/white_box/base.py
openvino_xai/methods/white_box/det_class_probability_map.py
openvino_xai/methods/white_box/recipro_cam.py
openvino_xai/methods/white_box/torch.py
openvino_xai/metrics/__init__.py
openvino_xai/metrics/adcc.py
openvino_xai/metrics/base.py
openvino_xai/metrics/insertion_deletion_auc.py
openvino_xai/metrics/pointing_game.py
openvino_xai/utils/__init__.py
openvino_xai/utils/model_export.py
openvino_xai/utils/torch.py
openvino_xai-1.1.0.dist-info/LICENSE
openvino_xai-1.1.0.dist-info/METADATA
openvino_xai-1.1.0.dist-info/WHEEL
openvino_xai-1.1.0.dist-info/top_level.txt
openvino_xai-1.1.0.dist-info/RECORD
