Metadata-Version: 2.1
Name: openvino_xai
Version: 1.1.0
Summary: OpenVINO™ Explainable AI (XAI) Toolkit: Visual Explanation for OpenVINO Models
Author: Intel(R) Corporation
Maintainer: Intel(R) Corporation
License: Apache License
Project-URL: Homepage, https://github.com/openvinotoolkit/openvino_xai
Project-URL: Documentation, https://openvinotoolkit.github.io/openvino_xai/
Project-URL: Repository, https://github.com/openvinotoolkit/openvino_xai.git
Keywords: openvino-toolkit,explainable-ai,xai,cnn,transformer,black-box,white-box
Classifier: License :: OSI Approved :: Apache Software License
Classifier: Programming Language :: Python :: 3.10
Classifier: Programming Language :: Python :: 3.11
Requires-Python: >=3.10
License-File: LICENSE
Requires-Dist: openvino-dev ==2024.4
Requires-Dist: opencv-python
Requires-Dist: scipy
Requires-Dist: numpy ==1.*
Requires-Dist: tqdm
Requires-Dist: matplotlib
Provides-Extra: dev
Requires-Dist: pytest ; extra == 'dev'
Requires-Dist: pytest-cov ; extra == 'dev'
Requires-Dist: pytest-csv ; extra == 'dev'
Requires-Dist: pytest-mock ; extra == 'dev'
Requires-Dist: pytest-xdist ; extra == 'dev'
Requires-Dist: pre-commit ==3.7.0 ; extra == 'dev'
Requires-Dist: addict ; extra == 'dev'
Requires-Dist: timm ==0.9.5 ; extra == 'dev'
Requires-Dist: onnx ; extra == 'dev'
Requires-Dist: onnxruntime ; extra == 'dev'
Requires-Dist: pandas ; extra == 'dev'
Requires-Dist: py-cpuinfo ; extra == 'dev'
Requires-Dist: openpyxl ; extra == 'dev'
Requires-Dist: torchvision ; extra == 'dev'
Requires-Dist: pycocotools ; extra == 'dev'
Provides-Extra: doc
Requires-Dist: furo ; extra == 'doc'
Requires-Dist: myst-parser ; extra == 'doc'
Requires-Dist: pydata-sphinx-theme ; extra == 'doc'
Requires-Dist: sphinx ; extra == 'doc'
Requires-Dist: sphinx-autoapi ; extra == 'doc'
Requires-Dist: sphinx-copybutton ; extra == 'doc'
Requires-Dist: sphinx-design ; extra == 'doc'
Requires-Dist: sphinx-panels ; extra == 'doc'
Requires-Dist: sphinx-tabs ; extra == 'doc'
Requires-Dist: sphinxemoji ; extra == 'doc'
